package_calculadora/__init__.py
package_calculadora/module1_name/__init__.py
package_calculadora/module1_name/calculadora.py
package_calculadora-0.0.1.dist-info/METADATA
package_calculadora-0.0.1.dist-info/WHEEL
package_calculadora-0.0.1.dist-info/top_level.txt
package_calculadora-0.0.1.dist-info/RECORD
